robogpt_client/__init__.py
robogpt_client/compile_proto.py
robogpt_client/agents/__init__.py
robogpt_client/agents/agent_client.py
robogpt_client/examples/__init__.py
robogpt_client/examples/demo_agents.py
robogpt_client/examples/demo_bot_control.py
robogpt_client/examples/demo_vision.py
robogpt_client/robot_control/__init__.py
robogpt_client/robot_control/bot_control_client.py
robogpt_client/vision/__init__.py
robogpt_client/vision/vision_client.py
robogpt_client-0.1.4.dist-info/METADATA
robogpt_client-0.1.4.dist-info/WHEEL
robogpt_client-0.1.4.dist-info/entry_points.txt
robogpt_client-0.1.4.dist-info/top_level.txt
robogpt_client-0.1.4.dist-info/RECORD
